optimum/commands/export/openvino.py
optimum/commands/neural_compressor/base.py
optimum/commands/neural_compressor/quantize.py
optimum/commands/register/register_inc.py
optimum/commands/register/register_openvino.py
optimum/exporters/ipex/__init__.py
optimum/exporters/ipex/cache_utils.py
optimum/exporters/ipex/model_config.py
optimum/exporters/ipex/model_patcher.py
optimum/exporters/ipex/modeling_utils.py
optimum/exporters/openvino/__init__.py
optimum/exporters/openvino/__main__.py
optimum/exporters/openvino/convert.py
optimum/exporters/openvino/model_configs.py
optimum/exporters/openvino/model_patcher.py
optimum/exporters/openvino/stateful.py
optimum/exporters/openvino/utils.py
optimum/intel/__init__.py
optimum/intel/version.py
optimum/intel/ipex/__init__.py
optimum/intel/ipex/modeling_base.py
optimum/intel/ipex/modeling_sentence_transformers.py
optimum/intel/ipex/utils.py
optimum/intel/neural_compressor/__init__.py
optimum/intel/neural_compressor/configuration.py
optimum/intel/neural_compressor/launcher.py
optimum/intel/neural_compressor/modeling_base.py
optimum/intel/neural_compressor/modeling_diffusion.py
optimum/intel/neural_compressor/neural_coder_adaptor.py
optimum/intel/neural_compressor/quantization.py
optimum/intel/neural_compressor/trainer.py
optimum/intel/neural_compressor/trainer_seq2seq.py
optimum/intel/neural_compressor/utils.py
optimum/intel/openvino/__init__.py
optimum/intel/openvino/configuration.py
optimum/intel/openvino/loaders.py
optimum/intel/openvino/modeling.py
optimum/intel/openvino/modeling_base.py
optimum/intel/openvino/modeling_decoder.py
optimum/intel/openvino/modeling_diffusion.py
optimum/intel/openvino/modeling_open_clip.py
optimum/intel/openvino/modeling_sam.py
optimum/intel/openvino/modeling_sentence_transformers.py
optimum/intel/openvino/modeling_seq2seq.py
optimum/intel/openvino/modeling_text2speech.py
optimum/intel/openvino/modeling_timm.py
optimum/intel/openvino/modeling_visual_language.py
optimum/intel/openvino/quantization.py
optimum_intel-1.26.1.dist-info/licenses/LICENSE
optimum_intel-1.26.1.dist-info/METADATA
optimum_intel-1.26.1.dist-info/WHEEL
optimum_intel-1.26.1.dist-info/entry_points.txt
optimum_intel-1.26.1.dist-info/top_level.txt
optimum_intel-1.26.1.dist-info/RECORD
